odoo/addons/product_packaging_dimension/README.rst
odoo/addons/product_packaging_dimension/__init__.py
odoo/addons/product_packaging_dimension/__manifest__.py
odoo/addons/product_packaging_dimension/i18n/ca.po
odoo/addons/product_packaging_dimension/i18n/de.po
odoo/addons/product_packaging_dimension/i18n/es.po
odoo/addons/product_packaging_dimension/i18n/it.po
odoo/addons/product_packaging_dimension/i18n/product_packaging_dimension.pot
odoo/addons/product_packaging_dimension/models/__init__.py
odoo/addons/product_packaging_dimension/models/product_packaging.py
odoo/addons/product_packaging_dimension/readme/CONTRIBUTORS.md
odoo/addons/product_packaging_dimension/readme/DESCRIPTION.md
odoo/addons/product_packaging_dimension/static/description/icon.png
odoo/addons/product_packaging_dimension/static/description/index.html
odoo/addons/product_packaging_dimension/tests/__init__.py
odoo/addons/product_packaging_dimension/tests/test_packaging_volume.py
odoo/addons/product_packaging_dimension/views/product_packaging.xml
odoo_addon_product_packaging_dimension-18.0.1.0.0.2.dist-info/METADATA
odoo_addon_product_packaging_dimension-18.0.1.0.0.2.dist-info/WHEEL
odoo_addon_product_packaging_dimension-18.0.1.0.0.2.dist-info/top_level.txt
odoo_addon_product_packaging_dimension-18.0.1.0.0.2.dist-info/RECORD
