Metadata-Version: 2.1
Name: odoo-addon-product_packaging_dimension
Version: 18.0.1.0.0.2
Requires-Python: >=3.10
Requires-Dist: odoo-addon-product_logistics_uom==18.0.*
Requires-Dist: odoo==18.0.*
Summary: Manage packaging dimensions and weight
Home-page: https://github.com/OCA/product-attribute
License: AGPL-3
Author: Camptocamp, Akretion, Odoo Community Association (OCA)
Author-email: support@odoo-community.org
Classifier: Programming Language :: Python
Classifier: Framework :: Odoo
Classifier: Framework :: Odoo :: 18.0
Classifier: License :: OSI Approved :: GNU Affero General Public License v3
